[
    [
        "Esc",
        "!\n1\n\nぬ",
        "@\n2\n\nふ",
        "#\n3\nぁ\nあ",
        "$\n4\nぅ\nう",
        "%\n5\nぇ\nえ",
        "^\n6\nぉ\nお",
        "&\n7\nゃ\nや",
        "*\n8\nゅ\nゆ",
        "(\n9\nょ\nよ",
        ")\n0\nを\nわ",
        "_\n-\nー\nほ",
        "+\n=\n\nへ",
        "|\n\\\n\nむ",
        "~\n`\n\nろ"
    ],
    [
        {"w": 1.5},
        "Tab",
        "Q\n\n\nた",
        "W\n\n\nて",
        "E\n\nぃ\nい",
        "R\n\n\nす",
        "T\n\n\nか",
        "Y\n\n\nん",
        "U\n\n\nな",
        "I\n\n\nに",
        "O\n\n\nら",
        "P\n\n\nせ",
        "{\n[\n「\n゛",
        "}\n]\n」\n゜",
        {"w": 1.5},
        "Delete"
    ],
    [
        {"w": 1.75},
        "Control",
        "A\n\n\nち",
        "S\n\n\nと",
        "D\n\n\nし",
        "F\n\n\nは",
        "G\n\n\nき",
        "H\n\n\nく",
        "J\n\n\nま",
        "K\n\n\nの",
        "L\n\n\nり",
        ":\n;\n\nれ",
        "\"\n'\n\nけ",
        {"w": 2.25},
        "Return"
    ],
    [
        {"w": 2.25},
        "Shift",
        "Z\n\nっ\nつ",
        "X\n\n\nさ",
        "C\n\n\nそ",
        "V\n\n\nひ",
        "B\n\n\nこ",
        "N\n\n\nみ",
        "M\n\n\nも",
        "<\n,\n、\nね",
        ">\n.\n。\nる",
        "?\n/\n・\nめ",
        {"w": 1.75},
        "Shift",
        "Fn"
    ],
    [
        {"x": 1.5},
        "Alt",
        {"w": 1.5},
        "◇",
        {"w": 6.0},
        "",
        {"w": 1.5},
        "◇",
        "Alt"
    ]
]
